azdatalakefacade/__init__.py
azdatalakefacade/singleton.py
azdatalakefacade-1.0.5.dist-info/LICENSE
azdatalakefacade-1.0.5.dist-info/METADATA
azdatalakefacade-1.0.5.dist-info/WHEEL
azdatalakefacade-1.0.5.dist-info/top_level.txt
azdatalakefacade-1.0.5.dist-info/RECORD
